jsonrpyc/__init__.py
jsonrpyc/__meta__.py
jsonrpyc-1.3.0.dist-info/LICENSE
jsonrpyc-1.3.0.dist-info/METADATA
jsonrpyc-1.3.0.dist-info/WHEEL
jsonrpyc-1.3.0.dist-info/top_level.txt
jsonrpyc-1.3.0.dist-info/RECORD
