Metadata-Version: 2.1
Name: jsonrpyc
Version: 1.3.0
Summary: Minimal python RPC implementation in a single file based on the JSON-RPC 2.0 specs from http://www.jsonrpc.org/specification.
Author-email: Marcel Rieger <github.riga@icloud.com>
License: Copyright (c) 2016-2024, Marcel Rieger
Project-URL: Homepage, https://github.com/riga/jsonrpyc
Project-URL: Documentation, https://jsonrpyc.readthedocs.io
Project-URL: Repository, https://github.com/riga/jsonrpyc.git
Keywords: rpc,json,json-rpc,jsonrpc,2.0
Classifier: Programming Language :: Python
Classifier: Programming Language :: Python :: 3
Classifier: Programming Language :: Python :: 3.8
Classifier: Programming Language :: Python :: 3.9
Classifier: Programming Language :: Python :: 3.10
Classifier: Programming Language :: Python :: 3.11
Classifier: Programming Language :: Python :: 3.12
Classifier: Operating System :: OS Independent
Classifier: License :: OSI Approved :: BSD License
Classifier: Intended Audience :: Developers
Classifier: Intended Audience :: Science/Research
Classifier: Intended Audience :: Information Technology
Requires-Python: >=3.8
License-File: LICENSE
Requires-Dist: typing-extensions ~=4.8
Provides-Extra: dev
Requires-Dist: mypy ~=1.9.0 ; extra == 'dev'
Requires-Dist: flake8 ~=7.0.0 ; extra == 'dev'
Requires-Dist: flake8-commas ~=2.1.0 ; extra == 'dev'
Requires-Dist: flake8-quotes ~=3.3.2 ; extra == 'dev'
Requires-Dist: pytest ~=7.4.4 ; extra == 'dev'
Requires-Dist: pytest-cov ~=4.1.0 ; extra == 'dev'
Requires-Dist: types-docutils ~=0.20.0 ; extra == 'dev'
Provides-Extra: docs
Requires-Dist: sphinx ~=6.2.1 ; extra == 'docs'
Requires-Dist: sphinx-book-theme ~=1.0.1 ; extra == 'docs'
Requires-Dist: sphinx-autodoc-typehints <1.23,~=1.22 ; extra == 'docs'
Requires-Dist: sphinx-lfs-content ~=1.1.7 ; extra == 'docs'
Requires-Dist: myst-parser ~=2.0.0 ; extra == 'docs'
